square/__init__.py
square/__main__.py
pysquare-1.0.0.dist-info/LICENSE
pysquare-1.0.0.dist-info/METADATA
pysquare-1.0.0.dist-info/WHEEL
pysquare-1.0.0.dist-info/entry_points.txt
pysquare-1.0.0.dist-info/top_level.txt
pysquare-1.0.0.dist-info/RECORD
